pyreflect/__init__.py
pyreflect/core/__init__.py
pyreflect/core/cache.py
pyreflect/core/python_types.py
pyreflect/core/reflect.py
pyreflect/core/represent.py
pyreflect/core/types.py
pyreflect/core/utils.py
pyreflect/core/abstract/__init__.py
pyreflect/core/abstract/parameters.py
pyreflect/core/abstract/parameters_builder.py
pyreflect/core/abstract/signature.py
pyreflect/core/base/__init__.py
pyreflect/core/base/function.py
pyreflect/core/base/module.py
pyreflect/core/base/object_base.py
pyreflect/core/base/parameter.py
pyreflect/core/base/type.py
pyreflect/core/code/__init__.py
pyreflect/core/code/code_object.py
pyreflect/core/code/disassembly.py
pyreflect/core/code/instruction.py
pyreflect/core/code/lib.py
pyreflect/core/reflected/__init__.py
pyreflect/core/reflected/reflected_bound_class_method.py
pyreflect/core/reflected/reflected_bound_method.py
pyreflect/core/reflected/reflected_class.py
pyreflect/core/reflected/reflected_class_method.py
pyreflect/core/reflected/reflected_function.py
pyreflect/core/reflected/reflected_method.py
pyreflect/core/reflected/reflected_module.py
pyreflect/core/reflected/reflected_object_base.py
pyreflect/core/reflected/reflected_partial.py
pyreflect/core/reflected/reflected_static_method.py
pyreflect/core/utils/__init__.py
pyreflect/core/utils/check.py
pyreflect/core/utils/convert.py
pyreflect/core/utils/get.py
pyreflect/core/utils/misc.py
pyreflect/core/utils/reflect.py
pyreflect/core/utils/represent.py
pyreflect-0.1.0.dist-info/METADATA
pyreflect-0.1.0.dist-info/WHEEL
pyreflect-0.1.0.dist-info/top_level.txt
pyreflect-0.1.0.dist-info/RECORD
