Metadata-Version: 2.1
Name: pyreflect
Version: 0.1.0
Summary: OOP approach for python reflection
Author-email: Xpo Development <dev@xpo.dev>
Classifier: Programming Language :: Python :: 3
Classifier: License :: OSI Approved :: MIT License
Classifier: Operating System :: OS Independent
Requires-Python: >=3.8
